microcli.py
setup.cfg
setup.py
microcli.egg-info/PKG-INFO
microcli.egg-info/SOURCES.txt
microcli.egg-info/dependency_links.txt
microcli.egg-info/top_level.txt