Metadata-Version: 1.0
Name: microcli
Version: 0.3.1
Summary: Extremely lightweight CLI lib for python
Home-page: https://github.com/neumark/microcli
Author: Peter Neumark
Author-email: neumark.peter@gmail.com
License: UNKNOWN
Download-URL: https://github.com/neumark/microcli
Platform: UNKNOWN
Classifier: Intended Audience :: Developers
Classifier: License :: OSI Approved :: Apache Software License
Classifier: Operating System :: OS Independent
Classifier: Programming Language :: Python
Classifier: Topic :: Software Development :: Libraries :: Python Modules
Classifier: Programming Language :: Python
Classifier: Programming Language :: Python :: 2
Classifier: Programming Language :: Python :: 2.6
Classifier: Programming Language :: Python :: 2.7
Classifier: Programming Language :: Python :: 3
Classifier: Programming Language :: Python :: 3.3
Classifier: Programming Language :: Python :: 3.4
